book_queue/__init__.py
book_queue/__main__.py
book_queue/main.py
book_queue-0.1.0.dist-info/entry_points.txt
book_queue-0.1.0.dist-info/WHEEL
book_queue-0.1.0.dist-info/METADATA
book_queue-0.1.0.dist-info/RECORD
