Metadata-Version: 2.1
Name: book-queue
Version: 0.1.0
Summary: 
Author: ShaddyDC
Author-email: shaddy@shaddy.dev
Requires-Python: >=3.10,<4.0
Classifier: Programming Language :: Python :: 3
Classifier: Programming Language :: Python :: 3.10
Requires-Dist: SQLAlchemy (>=1.4.34,<2.0.0)
Requires-Dist: tabulate (>=0.8.9,<0.9.0)
Requires-Dist: typer[all] (>=0.4.1,<0.5.0)
